winrmcp/__init__.py
winrmcp/client.py
winrmcp/copy.py
winrmcp-0.0.3.dist-info/LICENSE
winrmcp-0.0.3.dist-info/METADATA
winrmcp-0.0.3.dist-info/WHEEL
winrmcp-0.0.3.dist-info/top_level.txt
winrmcp-0.0.3.dist-info/RECORD
