Metadata-Version: 2.1
Name: winrmcp
Version: 0.0.3
Summary: Package to execute commads on remote Windows, do file copy to the remote machine
Home-page: https://github.com/mkroutikov/winrmcp
Author: Mike Kroutikov
Author-email: mkroutikov@innodata.com
License: MIT
Platform: UNKNOWN
Classifier: Development Status :: 4 - Beta
Classifier: Intended Audience :: Developers
Classifier: Programming Language :: Python :: 3 :: Only
Classifier: Programming Language :: Python :: 3.7
Classifier: Programming Language :: Python :: 3.8
Classifier: License :: OSI Approved :: MIT License
Classifier: Operating System :: OS Independent
Requires-Python: >=3.6
Requires-Dist: pywinrm
Provides-Extra: credssp
Requires-Dist: requests-credssp (>=1.0.0) ; extra == 'credssp'
Provides-Extra: kerberos
Requires-Dist: pykerberos (<2.0.0,>=1.2.1) ; (sys_platform!="win32") and extra == 'kerberos'
Requires-Dist: winkerberos (>=0.5.0) ; (sys_platform=="win32") and extra == 'kerberos'
